{
  "HALProvider": {
    "Other Devices": {
      "SPARK MAX [3]": {
        "header": {
          "open": true
        }
      }
    }
  },
  "NTProvider": {
    "types": {
      "/FMSInfo": "FMSInfo",
      "/Shuffleboard/Swerve Tester/Modules": "String Chooser",
      "/Shuffleboard/Swerve Tester/Test Routines": "String Chooser",
      "/SmartDashboard/Scheduler": "Scheduler"
    }
  },
  "NetworkTables": {
    "transitory": {
      "SmartDashboard": {
        "Scheduler": {
          "open": true
        },
        "open": true
      }
    }
  }
}
